lotusdb/__init__.py
lotusdb/database.py
lotusdb-0.1.1.dist-info/METADATA
lotusdb-0.1.1.dist-info/WHEEL
lotusdb-0.1.1.dist-info/top_level.txt
lotusdb-0.1.1.dist-info/RECORD
