Metadata-Version: 2.1
Name: lotusdb
Version: 0.1.1
Summary: pydb
Home-page: UNKNOWN
Author: d3tu
Author-email: jpafly@gmail.com
License: UNKNOWN
Keywords: database
Platform: UNKNOWN
Classifier: Development Status :: 1 - Planning
Classifier: Intended Audience :: Developers
Classifier: Programming Language :: Python :: 3
Classifier: Operating System :: Unix
Classifier: Operating System :: MacOS :: MacOS X
Classifier: Operating System :: Microsoft :: Windows
Requires-Dist: ujson
Requires-Dist: python-rapidjson
